kraken_user/__init__.py
kraken_user/class_kraken_user.py
kraken_user/class_kraken_users.py
kraken_user/flask_routes.py
kraken_user/kraken_user.py
kraken_user/helpers/__init__.py
kraken_user/helpers/json.py
kraken_user/helpers/things.py
kraken_user-0.0.19.dist-info/LICENSE.txt
kraken_user-0.0.19.dist-info/METADATA
kraken_user-0.0.19.dist-info/WHEEL
kraken_user-0.0.19.dist-info/top_level.txt
kraken_user-0.0.19.dist-info/RECORD
