Metadata-Version: 2.1
Name: kraken-user
Version: 0.0.19
Summary: kraken-user
Home-page: https://github.com/tactik8/krakenuser
Author: Tactik8
Author-email: info@tactik8.com
License: MIT
Classifier: License :: OSI Approved :: MIT License
Classifier: Programming Language :: Python :: 3
Classifier: Programming Language :: Python :: 3.10
License-File: LICENSE.txt
Requires-Dist: requests
Requires-Dist: flask
Requires-Dist: flask-login
